django_thumbnail_form_field-0.1.1.dist-info/licenses/LICENSE
thumbnail_field/__init__.py
thumbnail_field/forms.py
django_thumbnail_form_field-0.1.1.dist-info/METADATA
django_thumbnail_form_field-0.1.1.dist-info/WHEEL
django_thumbnail_form_field-0.1.1.dist-info/top_level.txt
django_thumbnail_form_field-0.1.1.dist-info/RECORD
