Metadata-Version: 2.4
Name: django-thumbnail-form-field
Version: 0.1.1
Summary: A small Django form ImageField that creates optimized thumbnails (WEBP default).
Author-email: "Eng. Naif" <eng.naif.shargabi@gmail.com>
License-Expression: MIT
Classifier: Framework :: Django
Classifier: Programming Language :: Python :: 3
Classifier: Operating System :: OS Independent
Requires-Python: >=3.8
License-File: LICENSE
Requires-Dist: Django>=3.2
Requires-Dist: Pillow>=9.0
Dynamic: license-file
